waterbg.py
waterbg-1.1.0.dist-info/LICENSE
waterbg-1.1.0.dist-info/METADATA
waterbg-1.1.0.dist-info/WHEEL
waterbg-1.1.0.dist-info/top_level.txt
waterbg-1.1.0.dist-info/RECORD
